chianode/__init__.py
chianode/constants.py
chianode/mojoclient.py
chianode/rpcclient.py
python_chianode-0.1.1.dist-info/METADATA
python_chianode-0.1.1.dist-info/WHEEL
python_chianode-0.1.1.dist-info/RECORD
